Workbook

Sheet Assumptions
A1: NPV Lab · Capital Planning Model Export
A2: npvlab.com · Export Date: June 06, 2026 · Add periods by extending column E rightward in DCF Model
A3: Blue = User input | Black = Formula | Green = Cross-sheet link
A5: MODEL INPUTS
A6: Parameter | B6: Value | C6: Notes
A7: Initial Investment | B7: 100000 | C7: Upfront capital outlay
A8: Hurdle Rate (Discount Rate) | B8: 0.1 | C8: WACC or required return on capital
A9: Sensitivity Threshold | B9: 0.15 | C9: Maximum acceptable variance in assumptions
A11: CASH FLOW PROJECTIONS
A12: Period | B12: Cash Flow ($) | C12: Notes
A13: Year 1 | B13: 35000 | C13: Operating cash flow
A14: Year 2 | B14: 40000 | C14: Operating cash flow
A15: Year 3 | B15: 50000 | C15: Operating cash flow + terminal residual

Sheet DCF Model
A1: DCF Model · All inputs link from Assumptions tab
A2: Extend column E rightward for more periods · Update NPV/IRR ranges in rows 14-15 accordingly
B4: Year 0 | C4: Year 1 | D4: Year 2 | E4: Year 3
A5: Period t = | B5: 0 | C5: 1 | D5: 2 | E5: 3 | F5: Reference only — drives discount factor formula
A6: Cash Flow ($) | B6: =-Assumptions!B7 -> -100000 | C6: =Assumptions!B13 -> 35000 | D6: =Assumptions!B14 -> 40000 | E6: =Assumptions!B15 -> 50000 | F6: Year 0 = negative initial outlay; Years 1+ = positive inflows
A7: Discount Factor | B7: =1 -> 1 | C7: =1/(1+Assumptions!$B$8)^C5 -> 0.90909091 | D7: =1/(1+Assumptions!$B$8)^D5 -> 0.82644628 | E7: =1/(1+Assumptions!$B$8)^E5 -> 0.7513148 | F7: Formula: 1 / (1 + Hurdle Rate)^t · Copy formula rightward for additional years
A8: Present Value ($) | B8: =B6*B7 -> -100000 | C8: =C6*C7 -> 31818.182 | D8: =D6*D7 -> 33057.851 | E8: =E6*E7 -> 37565.74 | F8: Cash Flow x Discount Factor
A9: Cumulative Cash Flow ($) | B9: =B6 -> -100000 | C9: =B9+C6 -> -65000 | D9: =C9+D6 -> -25000 | E9: =D9+E6 -> 25000 | F9: Running undiscounted total · Crosses $0 = simple payback point
A10: Cumulative PV ($) | B10: =B8 -> -100000 | C10: =B10+C8 -> -68181.818 | D10: =C10+D8 -> -35123.967 | E10: =D10+E8 -> 2441.7731 | F10: Running discounted total · Crosses $0 = discounted payback point (matches NPV Lab display)
A12: INVESTMENT SUMMARY
A13: Metric | B13: Value | C13: Formula Notes
A14: Net Present Value (NPV) | B14: =NPV(Assumptions!B8,C6,D6,E6)+B6 -> 2441.7731 | C14: NPV(rate, CF1..CFn) + Year 0 CF · Extend value range for more periods
A15: Internal Rate of Return (IRR) | B15: =IRR(B6:E6) -> 0.11300759 | C15: IRR(Year 0 CF : Last Year CF) · Extend range for more periods
A16: Simple Payback Period | B16: =IF(C9>=0,ABS(B9)/C6,IF(D9>=0,1+ABS(C9)/D6,IF(E9>=0,2+ABS(D9)/E6,"N/A"))) -> 2.5 | C16: Year of recovery + fractional interpolation (remaining balance / that year CF)
A17: Discounted Payback Period | B17: =IF(C10>=0,ABS(B10)/C8,IF(D10>=0,1+ABS(C10)/D8,IF(E10>=0,2+ABS(D10)/E8,"N/A"))) -> 2.935 | C17: Same logic using discounted PVs — mirrors NPV Lab display
A18: Return on Invested Capital | B18: =B14/ABS(B6) -> 0.024417731 | C18: NPV / Initial Investment · Quick measure of value created per $ deployed

Sheet Decision Analysis
A1: Decision Analysis · Powered by NPV Lab
A2: Replicates NPV Lab's judgment layer — answering 'should you trust this NPV?'
A4: DECISION SUMMARY
A5: Check | B5: Result | C5: Threshold / Benchmark | D5: Interpretation
A6: Creates Value (NPV > 0) | B6: =IF('DCF Model'!B14>0,"Pass","Fail") -> Pass | C6: $0 | D6: =IF('DCF Model'!B14>0,"NPV is "&TEXT('DCF Model'!B14,"$#,##0")&" — project returns more than the "&TEXT(Assumptions!B8,"0.0%")&" cost of capital.","NPV is "&TEXT('DCF Model'!B14,"$#,##0")&" — project destroys value at the "&TEXT(Assumptions!B8,"0.0%")&" hurdle. Do not proceed.") -> NPV is $2,442 — project returns more than the 10.0% cost of capital.
A7: IRR Spread (IRR minus Hurdle Rate) | B7: ='DCF Model'!B15-Assumptions!B8 -> 0.013007588 | C7: =Assumptions!B9 -> 0.15 | D7: =IF(B7<Assumptions!B9,"IRR of "&TEXT('DCF Model'!B15,"0.00%")&" is only "&TEXT(B7,"0.00%")&" above the "&TEXT(Assumptions!B8,"0.0%")&" hurdle — thinner than the "&TEXT(Assumptions!B9,"0%")&" sensitivity threshold.","IRR of "&TEXT('DCF Model'!B15,"0.00%")&" is "&TEXT(B7,"0.00%")&" above the "&TEXT(Assumptions!B8,"0.0%")&" hurdle — clears the "&TEXT(Assumptions!B9,"0%")&" sensitivity threshold.") -> IRR of 11.30% is only 1.30% above the 10.0% hurdle — thinner than the 15% sensitivity threshold.
A8: Spread Rating | B8: =IF(B7<Assumptions!B9,"Thin","Comfortable") -> Thin | C8: =Assumptions!B9 -> 0.15 | D8: =IF(B8="Thin","A "&TEXT(Assumptions!B9,"0%")&" adverse move in assumptions could eliminate the IRR advantage entirely. Primary risk flag.","Spread clears the "&TEXT(Assumptions!B9,"0%")&" sensitivity threshold. Comfortable margin of safety.") -> A 15% adverse move in assumptions could eliminate the IRR advantage entirely. Primary risk flag.
A9: Max Initial Investment (Break-Even Cost) | B9: =Assumptions!B7+'DCF Model'!B14 -> 102441.77 | C9: =Assumptions!B7 -> 100000 | D9: ="Paid "&TEXT(Assumptions!B7,"$#,##0")&". Break-even at "&TEXT(B9,"$#,##0")&" — buffer of "&TEXT(B9-Assumptions!B7,"$#,##0")&" ("&TEXT((B9-Assumptions!B7)/Assumptions!B7,"0.0%")&" of initial cost)." -> Paid $100,000. Break-even at $102,442 — buffer of $2,442 (2.4% of initial cost).
A10: Durability (Absorbs Sensitivity% Cost Overrun?) | B10: =IF(B9>=Assumptions!B7*(1+Assumptions!B9),"Pass","Fail") -> Fail | C10: =Assumptions!B7*(1+Assumptions!B9) -> 115000 | D10: =IF(B10="Fail","A "&TEXT(Assumptions!B9,"0%")&" cost overrun raises outlay to "&TEXT(Assumptions!B7*(1+Assumptions!B9),"$#,##0")&", above the "&TEXT(B9,"$#,##0")&" break-even. NPV turns negative. Thesis is fragile.","A "&TEXT(Assumptions!B9,"0%")&" cost overrun raises outlay to "&TEXT(Assumptions!B7*(1+Assumptions!B9),"$#,##0")&", still below the "&TEXT(B9,"$#,##0")&" break-even. Project can absorb this shock.") -> A 15% cost overrun raises outlay to $115,000, above the $102,442 break-even. NPV turns negative. Thesis is fragile.
A11: OVERALL VERDICT | B11: =IF('DCF Model'!B14<0,"Reject",IF(AND(B8="Comfortable",B10="Pass"),"Proceed","Cautious")) -> Cautious | C11: — | D11: =IF('DCF Model'!B14<0,"Project destroys value. NPV is "&TEXT('DCF Model'!B14,"$#,##0")&" at a "&TEXT(Assumptions!B8,"0.0%")&" hurdle. Do not invest.",IF(AND(B8="Comfortable",B10="Pass"),"Strong thesis. NPV positive, spread comfortable, survives a "&TEXT(Assumptions!B9,"0%")&" cost shock. Proceed subject to execution risk.","NPV is positive but fragile: "&IF(B8="Thin","spread of "&TEXT(B7,"0.00%")&" is below the "&TEXT(Assumptions!B9,"0%")&" threshold; ","spread is acceptable; ")&IF(B10="Fail","a "&TEXT(Assumptions!B9,"0%")&" cost overrun flips NPV negative.","durability check passed.")&" Proceed with active risk monitoring.")) -> NPV is positive but fragile: spread of 1.30% is below the 15% threshold; a 15% cost overrun flips NPV negative. Proceed with active risk monitoring.
A13: STRESS TEST
A14: Scenario | B14: Stressed Result | C14: Base Case | D14: What To Look For
A15: Cost Overrun (+Sensitivity%) | B15: ='DCF Model'!B14-Assumptions!B7*Assumptions!B9 -> -12558.227 | C15: ='DCF Model'!B14 -> 2441.7731 | D15: NPV if initial investment runs over by the sensitivity threshold · If negative: zero cushion on cost side
A16: Revenue Shortfall (-Sensitivity%) | B16: =NPV(Assumptions!B8,'DCF Model'!C6*(1-Assumptions!B9),'DCF Model'!D6*(1-Assumptions!B9),'DCF Model'!E6*(1-Assumptions!B9))+'DCF Model'!B6 -> -12924.493 | C16: ='DCF Model'!B14 -> 2441.7731 | D16: NPV if all positive cash flows disappoint by the sensitivity threshold · If negative: zero cushion on revenue side
A17: Margin of Safety (NPV / Initial) | B17: ='DCF Model'!B14/ABS('DCF Model'!B6) -> 0.024417731 | C17: =Assumptions!B9 -> 0.15 | D17: If margin of safety < sensitivity threshold: NPV does not have room to absorb a sensitivity-sized adverse move

Sheet NPV Curve
A1: NPV Curve · NPV vs. Discount Rate
A2: Select A4:B25 and Insert > Recommended Charts > Line to build the NPV curve · NPV = $0 at the IRR
A3: Hurdle Rate: | B3: =Assumptions!B8 -> 0.1 | C3: IRR (from DCF Model!B15) is the discount rate where the curve crosses $0
A4: Discount Rate | B4: NPV ($) | C4: Zone vs. Hurdle
A5: 0 | B5: =NPV(A5,'DCF Model'!C6,'DCF Model'!D6,'DCF Model'!E6)+'DCF Model'!B6 -> 25000 | C5: =IF(A5<Assumptions!$B$8,"Above Hurdle",IF(ABS(A5-Assumptions!$B$8)<0.005,"At Hurdle","Below Hurdle")) -> Above Hurdle
A6: 0.02 | B6: =NPV(A6,'DCF Model'!C6,'DCF Model'!D6,'DCF Model'!E6)+'DCF Model'!B6 -> 19876.593 | C6: =IF(A6<Assumptions!$B$8,"Above Hurdle",IF(ABS(A6-Assumptions!$B$8)<0.005,"At Hurdle","Below Hurdle")) -> Above Hurdle
A7: 0.04 | B7: =NPV(A7,'DCF Model'!C6,'DCF Model'!D6,'DCF Model'!E6)+'DCF Model'!B6 -> 15085.913 | C7: =IF(A7<Assumptions!$B$8,"Above Hurdle",IF(ABS(A7-Assumptions!$B$8)<0.005,"At Hurdle","Below Hurdle")) -> Above Hurdle
A8: 0.06 | B8: =NPV(A8,'DCF Model'!C6,'DCF Model'!D6,'DCF Model'!E6)+'DCF Model'!B6 -> 10599.69 | C8: =IF(A8<Assumptions!$B$8,"Above Hurdle",IF(ABS(A8-Assumptions!$B$8)<0.005,"At Hurdle","Below Hurdle")) -> Above Hurdle
A9: 0.08 | B9: =NPV(A9,'DCF Model'!C6,'DCF Model'!D6,'DCF Model'!E6)+'DCF Model'!B6 -> 6392.5723 | C9: =IF(A9<Assumptions!$B$8,"Above Hurdle",IF(ABS(A9-Assumptions!$B$8)<0.005,"At Hurdle","Below Hurdle")) -> Above Hurdle
A10: 0.1 | B10: =NPV(A10,'DCF Model'!C6,'DCF Model'!D6,'DCF Model'!E6)+'DCF Model'!B6 -> 2441.7731 | C10: =IF(A10<Assumptions!$B$8,"Above Hurdle",IF(ABS(A10-Assumptions!$B$8)<0.005,"At Hurdle","Below Hurdle")) -> At Hurdle
A11: 0.12 | B11: =NPV(A11,'DCF Model'!C6,'DCF Model'!D6,'DCF Model'!E6)+'DCF Model'!B6 -> -1273.2325 | C11: =IF(A11<Assumptions!$B$8,"Above Hurdle",IF(ABS(A11-Assumptions!$B$8)<0.005,"At Hurdle","Below Hurdle")) -> Below Hurdle
A12: 0.14 | B12: =NPV(A12,'DCF Model'!C6,'DCF Model'!D6,'DCF Model'!E6)+'DCF Model'!B6 -> -4770.9687 | C12: =IF(A12<Assumptions!$B$8,"Above Hurdle",IF(ABS(A12-Assumptions!$B$8)<0.005,"At Hurdle","Below Hurdle")) -> Below Hurdle
A13: 0.16 | B13: =NPV(A13,'DCF Model'!C6,'DCF Model'!D6,'DCF Model'!E6)+'DCF Model'!B6 -> -8068.1865 | C13: =IF(A13<Assumptions!$B$8,"Above Hurdle",IF(ABS(A13-Assumptions!$B$8)<0.005,"At Hurdle","Below Hurdle")) -> Below Hurdle
A14: 0.18 | B14: =NPV(A14,'DCF Model'!C6,'DCF Model'!D6,'DCF Model'!E6)+'DCF Model'!B6 -> -11180.062 | C14: =IF(A14<Assumptions!$B$8,"Above Hurdle",IF(ABS(A14-Assumptions!$B$8)<0.005,"At Hurdle","Below Hurdle")) -> Below Hurdle
A15: 0.2 | B15: =NPV(A15,'DCF Model'!C6,'DCF Model'!D6,'DCF Model'!E6)+'DCF Model'!B6 -> -14120.37 | C15: =IF(A15<Assumptions!$B$8,"Above Hurdle",IF(ABS(A15-Assumptions!$B$8)<0.005,"At Hurdle","Below Hurdle")) -> Below Hurdle
A16: 0.22 | B16: =NPV(A16,'DCF Model'!C6,'DCF Model'!D6,'DCF Model'!E6)+'DCF Model'!B6 -> -16901.635 | C16: =IF(A16<Assumptions!$B$8,"Above Hurdle",IF(ABS(A16-Assumptions!$B$8)<0.005,"At Hurdle","Below Hurdle")) -> Below Hurdle
A17: 0.24 | B17: =NPV(A17,'DCF Model'!C6,'DCF Model'!D6,'DCF Model'!E6)+'DCF Model'!B6 -> -19535.262 | C17: =IF(A17<Assumptions!$B$8,"Above Hurdle",IF(ABS(A17-Assumptions!$B$8)<0.005,"At Hurdle","Below Hurdle")) -> Below Hurdle
A18: 0.26 | B18: =NPV(A18,'DCF Model'!C6,'DCF Model'!D6,'DCF Model'!E6)+'DCF Model'!B6 -> -22031.658 | C18: =IF(A18<Assumptions!$B$8,"Above Hurdle",IF(ABS(A18-Assumptions!$B$8)<0.005,"At Hurdle","Below Hurdle")) -> Below Hurdle
A19: 0.28 | B19: =NPV(A19,'DCF Model'!C6,'DCF Model'!D6,'DCF Model'!E6)+'DCF Model'!B6 -> -24400.33 | C19: =IF(A19<Assumptions!$B$8,"Above Hurdle",IF(ABS(A19-Assumptions!$B$8)<0.005,"At Hurdle","Below Hurdle")) -> Below Hurdle
A20: 0.3 | B20: =NPV(A20,'DCF Model'!C6,'DCF Model'!D6,'DCF Model'!E6)+'DCF Model'!B6 -> -26649.977 | C20: =IF(A20<Assumptions!$B$8,"Above Hurdle",IF(ABS(A20-Assumptions!$B$8)<0.005,"At Hurdle","Below Hurdle")) -> Below Hurdle
A21: 0.32 | B21: =NPV(A21,'DCF Model'!C6,'DCF Model'!D6,'DCF Model'!E6)+'DCF Model'!B6 -> -28788.574 | C21: =IF(A21<Assumptions!$B$8,"Above Hurdle",IF(ABS(A21-Assumptions!$B$8)<0.005,"At Hurdle","Below Hurdle")) -> Below Hurdle
A22: 0.34 | B22: =NPV(A22,'DCF Model'!C6,'DCF Model'!D6,'DCF Model'!E6)+'DCF Model'!B6 -> -30823.439 | C22: =IF(A22<Assumptions!$B$8,"Above Hurdle",IF(ABS(A22-Assumptions!$B$8)<0.005,"At Hurdle","Below Hurdle")) -> Below Hurdle
A23: 0.36 | B23: =NPV(A23,'DCF Model'!C6,'DCF Model'!D6,'DCF Model'!E6)+'DCF Model'!B6 -> -32761.297 | C23: =IF(A23<Assumptions!$B$8,"Above Hurdle",IF(ABS(A23-Assumptions!$B$8)<0.005,"At Hurdle","Below Hurdle")) -> Below Hurdle
A24: 0.38 | B24: =NPV(A24,'DCF Model'!C6,'DCF Model'!D6,'DCF Model'!E6)+'DCF Model'!B6 -> -34608.336 | C24: =IF(A24<Assumptions!$B$8,"Above Hurdle",IF(ABS(A24-Assumptions!$B$8)<0.005,"At Hurdle","Below Hurdle")) -> Below Hurdle
A25: 0.4 | B25: =NPV(A25,'DCF Model'!C6,'DCF Model'!D6,'DCF Model'!E6)+'DCF Model'!B6 -> -36370.262 | C25: =IF(A25<Assumptions!$B$8,"Above Hurdle",IF(ABS(A25-Assumptions!$B$8)<0.005,"At Hurdle","Below Hurdle")) -> Below Hurdle
